constance/__init__.py
constance/settings.py
settings/__init__.py
flask_redis_constance-0.0.9.dist-info/LICENCE
flask_redis_constance-0.0.9.dist-info/METADATA
flask_redis_constance-0.0.9.dist-info/WHEEL
flask_redis_constance-0.0.9.dist-info/top_level.txt
flask_redis_constance-0.0.9.dist-info/RECORD
